athena_bridge/__init__.py
athena_bridge/athenareader.py
athena_bridge/data_types.py
athena_bridge/dataframe.py
athena_bridge/dataframewriter.py
athena_bridge/dataproc_athena_bridge.py
athena_bridge/functions.py
athena_bridge/spark_athena_bridge.py
athena_bridge/window.py
athena_bridge-0.0.4.dist-info/licenses/LICENSE
athena_bridge-0.0.4.dist-info/METADATA
athena_bridge-0.0.4.dist-info/WHEEL
athena_bridge-0.0.4.dist-info/top_level.txt
athena_bridge-0.0.4.dist-info/RECORD
