Metadata-Version: 2.4
Name: athena_bridge
Version: 0.0.4
Summary: athena_bridge lets you run PySpark-style code using Python + AWS Athena, replicating PySpark’s syntax and functions. Write new code or migrate existing ones without EMR or Glue, leveraging Athena to cut costs and boost performance.
Author-email: Alvaro del Monte <author@example.com>
License-Expression: MIT
Project-URL: Homepage, https://github.com/AlvaroMF83/athena_bridge
Project-URL: Issues, https://github.com/AlvaroMF83/athena_bridge/issues
Classifier: Programming Language :: Python :: 3
Classifier: Operating System :: OS Independent
Requires-Python: >=3.9
License-File: LICENSE
Requires-Dist: awswrangler>=3.10.0
Dynamic: license-file
